{
    "wallpaper": "/home/fvb/Pictures/wallhaven-nrqpm4_2560x1080.png",
    "alpha": "100",
    "special": {
        "background": "#090909",
        "foreground": "#f0f0f0",
        "cursor": "#f0f0f0"
    },
    "colors": {
        "color0": "#090909",
        "color1": "#C4C4C4",
        "color2": "#CCCCCC",
        "color3": "#D4D4D4",
        "color4": "#DBDBDB",
        "color5": "#E4E4E4",
        "color6": "#ECECEC",
        "color7": "#f0f0f0",
        "color8": "#a8a8a8",
        "color9": "#C4C4C4",
        "color10": "#CCCCCC",
        "color11": "#D4D4D4",
        "color12": "#DBDBDB",
        "color13": "#E4E4E4",
        "color14": "#ECECEC",
        "color15": "#f0f0f0"
    }
}